actionscicd/__init__.py
actionscicd/somecode.py
actionscicd/data/__init__.py
actionscicd/data/mogi_data.tsv
tests/__init__.py
tests/test_somecode.py
github_actions_cicd_example-0.0.1.dist-info/LICENSE
github_actions_cicd_example-0.0.1.dist-info/METADATA
github_actions_cicd_example-0.0.1.dist-info/WHEEL
github_actions_cicd_example-0.0.1.dist-info/top_level.txt
github_actions_cicd_example-0.0.1.dist-info/RECORD
