Metadata-Version: 2.1
Name: github-actions-cicd-example
Version: 0.0.1
Summary: Test CI and automated code coverage reports using GitHub Actions.
Home-page: https://github.com/alexmalins/github-actions-cicd-example
Author: Alex Malins
Author-email: github@alexmalinsREMOVETHIS.com
License: MIT
Project-URL: Source, https://github.com/alexmalins/github-actions-cicd-example
Project-URL: Tracker, https://github.com/alexmalins/github-actions-cicd-example/issues
Project-URL: Documentation, https://alexmalins.github.io/github-actions-cicd-example
Platform: UNKNOWN
Classifier: Programming Language :: Python :: 3
Classifier: Programming Language :: Python :: 3 :: Only
Classifier: Programming Language :: Python :: 3.7
Classifier: Programming Language :: Python :: 3.8
Classifier: Programming Language :: Python :: 3.9
Classifier: Programming Language :: Python :: 3.10
Classifier: License :: OSI Approved :: MIT License
Classifier: Operating System :: OS Independent
Classifier: Development Status :: 1 - Planning
Requires-Python: >=3.7
Requires-Dist: numpy
